[{"__jsonclass__": ["sphinx_polyversion.git.GitRef", ["master", "ce934b63881bf3be4db045e42b12762892de5cf5", "refs/heads/master", {"__jsonclass__": ["sphinx_polyversion.git.GitRefType", "BRANCH"]}, {"__jsonhook__": ["sphinx_polyversion.json.std_hook", ".datetime", "2025-09-23T12:02:02+02:00"]}, null]]}, {"__jsonclass__": ["sphinx_polyversion.git.GitRef", ["v0.9.10", "609b33dba01b81d155cbb1ba2b15afb20f07cae1", "refs/tags/v0.9.10", {"__jsonclass__": ["sphinx_polyversion.git.GitRefType", "TAG"]}, {"__jsonhook__": ["sphinx_polyversion.json.std_hook", ".datetime", "2025-03-12T10:15:11+01:00"]}, null]]}]